pyzusi3/__init__.py
pyzusi3/client.py
pyzusi3/exceptions.py
pyzusi3/messagecoders.py
pyzusi3/messages.py
pyzusi3/nodes.py
pyzusi3/tests/__init__.py
pyzusi3/tests/test_messagecoders.py
pyzusi3/tests/test_messages.py
pyzusi3/tests/test_nodes.py
pyzusi3-3.1.0.dist-info/LICENSE
pyzusi3-3.1.0.dist-info/METADATA
pyzusi3-3.1.0.dist-info/WHEEL
pyzusi3-3.1.0.dist-info/top_level.txt
pyzusi3-3.1.0.dist-info/RECORD
