Metadata-Version: 2.1
Name: pyzusi3
Version: 3.1.0
Summary: Zusi3 TCP Client library with async support and no deps
License: BSD 3-Clause License
Keywords: tcp,async
Classifier: Programming Language :: Python :: 3
Requires-Python: >=3.10.7
License-File: LICENSE
